<?xml version="1.0" encoding="utf-8"?>
<publishData>
  <publishProfile publishUrl="C:\Users\Santhosh\Desktop\MyWorks\D2H\charityreceiptor\Publish" deleteExistingFiles="False" ftpAnonymousLogin="False" ftpPassiveMode="True" msdeploySite="" msdeploySiteID="" msdeployRemoteSitePhysicalPath="" msdeployAllowUntrustedCertificate="False" msdeploySkipExtraFilesOnServer="True" msdeployMarkAsApp="False" profileName="Profile1" publishMethod="FileSystem" replaceMatchingFiles="True" userName="" savePWD="False" userPWD="" SelectedForPublish="True">
    <file relUrl="Views/Controlpanel/Home.aspx" publishTime="01/29/2012 16:13:09" />
    <file relUrl="Images/gallery/thumb/img5.jpg" publishTime="01/10/2012 15:50:00" />
    <file relUrl="Images/gallery/saibaba128.jpg" publishTime="01/10/2012 15:49:59" />
    <file relUrl="Images/nextPageArrow.gif" publishTime="01/10/2012 15:50:00" />
    <file relUrl="Images/gallery/thumb/saibaba118.jpg" publishTime="01/10/2012 15:50:00" />
    <file relUrl="Images/gallery/saibaba64.JPG" publishTime="01/10/2012 15:49:59" />
    <file relUrl="Images/ui-icons_ffd27a_256x240.png" publishTime="01/10/2012 15:50:00" />
    <file relUrl="Images/gallery/saibaba39.JPG" publishTime="01/10/2012 15:49:59" />
    <file relUrl="Images/ui-icons_228ef1_256x240.png" publishTime="01/10/2012 15:50:00" />
    <file relUrl="Views/Controlpanel/Users.aspx" publishTime="01/10/2012 20:58:10" />
    <file relUrl="Images/gallery/saibaba77.JPG" publishTime="01/10/2012 15:49:59" />
    <file relUrl="Images/ui-icons_222222_256x240.png" publishTime="01/10/2012 15:50:00" />
    <file relUrl="Images/gallery/saibaba51.JPG" publishTime="01/10/2012 15:49:59" />
    <file relUrl="Images/gallery/saibaba25.JPG" publishTime="01/10/2012 15:49:59" />
    <file relUrl="Images/fancybox/fancy_close.png" publishTime="01/10/2012 15:49:59" />
    <file relUrl="Images/prevPageArrowWhite.gif" publishTime="01/10/2012 15:50:00" />
    <file relUrl="Images/gallery/thumb/saibaba113.jpg" publishTime="01/10/2012 15:50:00" />
    <file relUrl="Images/rt-pan-botrit.gif" publishTime="01/10/2012 15:50:00" />
    <file relUrl="Images/gallery/saibaba13.JPG" publishTime="01/10/2012 15:49:59" />
    <file relUrl="Images/fancybox/fancy_shadow_se.png" publishTime="01/10/2012 15:49:59" />
    <file relUrl="Images/gallery/saibaba60.JPG" publishTime="01/10/2012 15:49:59" />
    <file relUrl="Images/gallery/thumb/saibaba8.jpg" publishTime="01/10/2012 15:50:00" />
    <file relUrl="Images/remove.jpg" publishTime="01/26/2012 11:11:07" />
    <file relUrl="Images/gallery/saibaba82.JPG" publishTime="01/10/2012 15:50:00" />
    <file relUrl="Images/gallery/thumb/saibaba116.jpg" publishTime="01/10/2012 15:50:00" />
    <file relUrl="Images/gallery/saibaba73.JPG" publishTime="01/10/2012 15:49:59" />
    <file relUrl="Images/gallery/saibaba112.JPG" publishTime="01/10/2012 15:49:59" />
    <file relUrl="Images/gallery/saibaba83.JPG" publishTime="01/10/2012 15:50:00" />
    <file relUrl="Images/gallery/thumb/saibaba117.jpg" publishTime="01/10/2012 15:50:00" />
    <file relUrl="Images/gallery/saibaba101.JPG" publishTime="01/10/2012 15:49:59" />
    <file relUrl="Images/gallery/saibaba4.JPG" publishTime="01/10/2012 15:49:59" />
    <file relUrl="Images/gallery/saibaba17.JPG" publishTime="01/10/2012 15:49:59" />
    <file relUrl="Images/gallery/thumb/saibaba.jpg" publishTime="01/10/2012 15:50:00" />
    <file relUrl="Images/gallery/saibaba49.JPG" publishTime="01/10/2012 15:49:59" />
    <file relUrl="Images/Edit.gif" publishTime="01/10/2012 15:49:59" />
    <file relUrl="Views/Home/PrintRegularReceipt.aspx" publishTime="01/29/2012 11:43:20" />
    <file relUrl="Images/Copy of nav_ryt_img_bg.jpg" publishTime="01/10/2012 15:49:59" />
    <file relUrl="Images/gallery/saibaba121.jpg" publishTime="01/10/2012 15:49:59" />
    <file relUrl="Images/gallery/saibaba93.JPG" publishTime="01/10/2012 15:50:00" />
    <file relUrl="Images/gallery/saibaba86.JPG" publishTime="01/10/2012 15:50:00" />
    <file relUrl="Images/gallery/saibaba116.JPG" publishTime="01/10/2012 15:49:59" />
    <file relUrl="Scripts/jquery.highlight-3.js" publishTime="01/10/2012 15:50:00" />
    <file relUrl="Images/gallery/saibaba87.JPG" publishTime="01/10/2012 15:50:00" />
    <file relUrl="Images/gallery/img2.jpg" publishTime="01/10/2012 15:49:59" />
    <file relUrl="Content/themes/base/jquery.ui.tabs.css" publishTime="01/10/2012 15:49:59" />
    <file relUrl="Images/gallery/saibaba88.JPG" publishTime="01/10/2012 15:50:00" />
    <file relUrl="Images/ui-bg_glass_100_fdf5ce_1x400.png" publishTime="01/10/2012 15:50:00" />
    <file relUrl="Images/comingsoon.gif" publishTime="01/10/2012 15:49:59" />
    <file relUrl="Scripts/jquery-1.5.1-vsdoc.js" publishTime="01/10/2012 15:50:00" />
    <file relUrl="Images/gallery/saibaba67.JPG" publishTime="01/10/2012 15:49:59" />
    <file relUrl="Images/gallery/saibaba125.jpg" publishTime="01/10/2012 15:49:59" />
    <file relUrl="Images/ui-bg_diagonals-thick_20_666666_40x40.png" publishTime="01/10/2012 15:50:00" />
    <file relUrl="Images/gallery/saibaba58.JPG" publishTime="01/10/2012 15:49:59" />
    <file relUrl="Views/Reports/RecurringReceipts.aspx" publishTime="01/26/2012 14:16:17" />
    <file relUrl="Images/gallery/thumb/saibaba110.jpg" publishTime="01/10/2012 15:50:00" />
    <file relUrl="Scripts/jquery-1.5.1.min.js" publishTime="01/10/2012 15:50:00" />
    <file relUrl="Scripts/modernizr-1.7.min.js" publishTime="01/10/2012 15:50:00" />
    <file relUrl="Images/gallery/thumb/saibaba1.jpg" publishTime="01/10/2012 15:50:00" />
    <file relUrl="Scripts/jquery.galleriffic.js" publishTime="01/10/2012 15:50:00" />
    <file relUrl="Images/gallery/saibaba59.JPG" publishTime="01/10/2012 15:49:59" />
    <file relUrl="Images/gallery/saibaba89.JPG" publishTime="01/10/2012 15:50:00" />
    <file relUrl="Scripts/modernizr-1.7.js" publishTime="01/10/2012 15:50:00" />
    <file relUrl="Content/stylesheet.css" publishTime="01/26/2012 12:50:08" />
    <file relUrl="Images/gallery/saibaba63.JPG" publishTime="01/10/2012 15:49:59" />
    <file relUrl="Views/Reports/SearchReceipts.aspx" publishTime="01/29/2012 16:11:17" />
    <file relUrl="Content/themes/base/images/ui-bg_flat_75_ffffff_40x100.png" publishTime="01/10/2012 15:49:59" />
    <file relUrl="Images/gallery/saibaba46.JPG" publishTime="01/10/2012 15:49:59" />
    <file relUrl="Images/gallery/saibaba8.JPG" publishTime="01/10/2012 15:49:59" />
    <file relUrl="Images/gallery/saibaba111.JPG" publishTime="01/10/2012 15:49:59" />
    <file relUrl="Images/gallery/saibaba47.JPG" publishTime="01/10/2012 15:49:59" />
    <file relUrl="Images/rt-pan-toplet.gif" publishTime="01/10/2012 15:50:00" />
    <file relUrl="Images/gallery/thumb/saibaba104.jpg" publishTime="01/10/2012 15:50:00" />
    <file relUrl="Images/saibaba-2.png" publishTime="01/10/2012 15:50:00" />
    <file relUrl="Images/gallery/saibaba20.JPG" publishTime="01/10/2012 15:49:59" />
    <file relUrl="Images/saibaba-3.png" publishTime="01/10/2012 15:50:00" />
    <file relUrl="Scripts/jquery-1.6.2.min.js" publishTime="01/10/2012 15:50:00" />
    <file relUrl="Content/themes/base/jquery.ui.dialog.css" publishTime="01/10/2012 15:49:59" />
    <file relUrl="Images/foot_rt.gif" publishTime="01/10/2012 15:49:59" />
    <file relUrl="Images/gallery/saibaba109.JPG" publishTime="01/10/2012 15:49:59" />
    <file relUrl="Images/gallery/saibaba10.JPG" publishTime="01/10/2012 15:49:59" />
    <file relUrl="Scripts/jquery.validate-vsdoc.js" publishTime="01/10/2012 15:50:00" />
    <file relUrl="Images/gallery/saibaba43.JPG" publishTime="01/10/2012 15:49:59" />
    <file relUrl="Images/ui-bg_glass_100_f6f6f6_1x400.png" publishTime="01/10/2012 15:50:00" />
    <file relUrl="Images/ui-bg_highlight-soft_100_eeeeee_1x100.png" publishTime="01/10/2012 15:50:00" />
    <file relUrl="Images/Updated-ramnavami.jpg" publishTime="01/10/2012 15:49:59" />
    <file relUrl="Images/prevPageArrow.gif" publishTime="01/10/2012 15:50:00" />
    <file relUrl="Images/header_image_bg.jpg" publishTime="01/10/2012 15:50:00" />
    <file relUrl="Images/fancybox/fancy_nav_right.png" publishTime="01/10/2012 15:49:59" />
    <file relUrl="Images/gallery/saibaba11.JPG" publishTime="01/10/2012 15:49:59" />
    <file relUrl="Images/rt-pan-toprit.gif" publishTime="01/10/2012 15:50:00" />
    <file relUrl="Images/page_container_img_bg.png" publishTime="01/10/2012 15:50:00" />
    <file relUrl="Scripts/receiptor.js" publishTime="01/26/2012 11:52:01" />
    <file relUrl="bin/BarcodeGenerator.1D.dll" publishTime="05/03/2009 14:09:50" />
    <file relUrl="Images/gallery/thumb/saibaba108.jpg" publishTime="01/10/2012 15:50:00" />
    <file relUrl="Images/fancybox/fancy_title_right.png" publishTime="01/10/2012 15:49:59" />
    <file relUrl="Images/gallery/saibaba14.JPG" publishTime="01/10/2012 15:49:59" />
    <file relUrl="Images/gallery/saibaba80.JPG" publishTime="01/10/2012 15:49:59" />
    <file relUrl="Scripts/jquery.validate.unobtrusive.min.js" publishTime="01/10/2012 15:50:00" />
    <file relUrl="Images/gallery/saibaba122.jpg" publishTime="01/10/2012 15:49:59" />
    <file relUrl="Images/gallery/saibaba81.JPG" publishTime="01/10/2012 15:50:00" />
    <file relUrl="Images/ui-bg_gloss-wave_35_f6a828_500x100.png" publishTime="01/10/2012 15:50:00" />
    <file relUrl="Images/fancybox/fancybox.png" publishTime="01/10/2012 15:49:59" />
    <file relUrl="Images/fancybox/fancy_shadow_sw.png" publishTime="01/10/2012 15:49:59" />
    <file relUrl="Images/gallery/saibaba33.JPG" publishTime="01/10/2012 15:49:59" />
    <file relUrl="Views/Home/RegularReceipt.aspx" publishTime="01/26/2012 12:18:38" />
    <file relUrl="Images/gallery/saibaba15.JPG" publishTime="01/10/2012 15:49:59" />
    <file relUrl="Images/gallery/img1.jpg" publishTime="01/10/2012 15:49:59" />
    <file relUrl="Scripts/jquery.fancybox-1.3.4.pack.js" publishTime="01/10/2012 15:50:00" />
    <file relUrl="Views/Shared/Status_Ctrl.ascx" publishTime="01/29/2012 14:06:56" />
    <file relUrl="Images/gallery/thumb/img2.jpg" publishTime="01/10/2012 15:50:00" />
    <file relUrl="Images/foot_lt.gif" publishTime="01/10/2012 15:49:59" />
    <file relUrl="Content/themes/base/images/ui-icons_cd0a0a_256x240.png" publishTime="01/10/2012 15:49:59" />
    <file relUrl="Images/gallery/saibaba84.JPG" publishTime="01/10/2012 15:50:00" />
    <file relUrl="Content/themes/base/images/ui-bg_glass_75_dadada_1x400.png" publishTime="01/10/2012 15:49:59" />
    <file relUrl="Images/fancybox/fancybox-x.png" publishTime="01/10/2012 15:49:59" />
    <file relUrl="bin/saibabacharityreceiptorDL.dll" publishTime="01/30/2012 17:47:21" />
    <file relUrl="Scripts/jquery.mousewheel-3.0.4.pack.js" publishTime="01/10/2012 15:50:00" />
    <file relUrl="Images/gallery/thumb/saibaba6.jpg" publishTime="01/10/2012 15:50:00" />
    <file relUrl="Images/gallery/saibaba85.JPG" publishTime="01/10/2012 15:50:00" />
    <file relUrl="bin/Telerik.OpenAccess.Query.dll" publishTime="04/05/2009 22:39:40" />
    <file relUrl="Views/Home/PrintRecurringReceipt.aspx" publishTime="01/29/2012 11:43:20" />
    <file relUrl="Images/gallery/saibaba37.JPG" publishTime="01/10/2012 15:49:59" />
    <file relUrl="Images/gallery/saibaba118.JPG" publishTime="01/10/2012 15:49:59" />
    <file relUrl="Images/gallery/saibaba119.JPG" publishTime="01/10/2012 15:49:59" />
    <file relUrl="Images/gallery/img5.jpg" publishTime="01/10/2012 15:49:59" />
    <file relUrl="todo.txt" publishTime="01/26/2012 11:11:07" />
    <file relUrl="Content/receipt.css" publishTime="01/29/2012 12:00:08" />
    <file relUrl="Images/rt-pan-mid.gif" publishTime="01/10/2012 15:50:00" />
    <file relUrl="Views/Account/LogOn.aspx" publishTime="01/26/2012 12:53:50" />
    <file relUrl="Content/themes/base/images/ui-icons_454545_256x240.png" publishTime="01/10/2012 15:49:59" />
    <file relUrl="Images/gallery/img4.jpg" publishTime="01/10/2012 15:49:59" />
    <file relUrl="Images/bg.gif" publishTime="01/10/2012 15:49:59" />
    <file relUrl="Images/gallery/saibaba18.JPG" publishTime="01/10/2012 15:49:59" />
    <file relUrl="Views/Home/EditRegularReceipt.aspx" publishTime="01/26/2012 12:34:57" />
    <file relUrl="Content/themes/base/images/ui-bg_flat_0_aaaaaa_40x100.png" publishTime="01/10/2012 15:49:59" />
    <file relUrl="Views/Home/EditRecurringReceipt.aspx" publishTime="01/26/2012 14:12:48" />
    <file relUrl="Views/Shared/PartialViewStatus.aspx" publishTime="01/10/2012 20:10:56" />
    <file relUrl="Images/gallery/saibaba44.JPG" publishTime="01/10/2012 15:49:59" />
    <file relUrl="Images/gallery/saibaba123.jpg" publishTime="01/10/2012 15:49:59" />
    <file relUrl="Views/Shared/CreateUser.ascx" publishTime="01/11/2012 16:32:00" />
    <file relUrl="Images/bullet.gif" publishTime="01/10/2012 15:49:59" />
    <file relUrl="Content/jquery.fancybox-1.3.4.css" publishTime="01/26/2012 13:02:16" />
    <file relUrl="Global.asax" publishTime="01/10/2012 15:49:59" />
    <file relUrl="Images/gallery/saibaba45.JPG" publishTime="01/10/2012 15:49:59" />
    <file relUrl="Images/gallery/saibaba23.JPG" publishTime="01/10/2012 15:49:59" />
    <file relUrl="Images/gallery/saibaba70.JPG" publishTime="01/10/2012 15:49:59" />
    <file relUrl="Images/fancybox/fancy_title_over.png" publishTime="01/10/2012 15:49:59" />
    <file relUrl="Images/ui-icons_ef8c08_256x240.png" publishTime="01/10/2012 15:50:00" />
    <file relUrl="Images/gallery/saibaba7.JPG" publishTime="01/10/2012 15:49:59" />
    <file relUrl="Images/gallery/saibaba28.JPG" publishTime="01/10/2012 15:49:59" />
    <file relUrl="Images/gallery/thumb/saibaba100.jpg" publishTime="01/10/2012 15:50:00" />
    <file relUrl="Images/gallery/saibaba66.JPG" publishTime="01/10/2012 15:49:59" />
    <file relUrl="Images/gallery/saibaba40.JPG" publishTime="01/10/2012 15:49:59" />
    <file relUrl="Images/navBar_bg.jpg" publishTime="01/10/2012 15:50:00" />
    <file relUrl="Images/gallery/saibaba41.JPG" publishTime="01/10/2012 15:49:59" />
    <file relUrl="Images/gallery/saibaba27.JPG" publishTime="01/10/2012 15:49:59" />
    <file relUrl="Images/saibaba-1.png" publishTime="01/10/2012 15:50:00" />
    <file relUrl="Scripts/MicrosoftAjax.debug.js" publishTime="01/10/2012 15:50:00" />
    <file relUrl="Images/gallery/thumb/saibaba111.jpg" publishTime="01/10/2012 15:50:00" />
    <file relUrl="Images/page_cont_ryt_img_bg.jpg" publishTime="01/10/2012 15:50:00" />
    <file relUrl="Images/gallery/saibaba106.JPG" publishTime="01/10/2012 15:49:59" />
    <file relUrl="Views/Home/PrintMerchandiseReport.aspx" publishTime="01/29/2012 11:43:20" />
    <file relUrl="Images/ui-icons_ffffff_256x240.png" publishTime="01/10/2012 15:50:00" />
    <file relUrl="Scripts/jquery.unobtrusive-ajax.js" publishTime="01/10/2012 15:50:00" />
    <file relUrl="Images/gallery/saibaba62.JPG" publishTime="01/10/2012 15:49:59" />
    <file relUrl="Images/gallery/saibaba97.JPG" publishTime="01/10/2012 15:50:00" />
    <file relUrl="abouttemple.htm" publishTime="01/10/2012 15:50:00" />
    <file relUrl="gallery.html" publishTime="01/10/2012 15:50:00" />
    <file relUrl="Images/gallery/saibaba110.JPG" publishTime="01/10/2012 15:49:59" />
    <file relUrl="Images/mailer.jpg" publishTime="01/10/2012 15:50:00" />
    <file relUrl="Images/ui-bg_flat_10_000000_40x100.png" publishTime="01/10/2012 15:50:00" />
    <file relUrl="Images/gallery/saibaba19.JPG" publishTime="01/10/2012 15:49:59" />
    <file relUrl="Scripts/jquery-ui-1.8.11.min.js" publishTime="01/10/2012 15:50:00" />
    <file relUrl="Images/gallery/saibaba92.JPG" publishTime="01/10/2012 15:50:00" />
    <file relUrl="Content/document.css" publishTime="01/26/2012 12:50:45" />
    <file relUrl="Images/fancybox/fancy_title_main.png" publishTime="01/10/2012 15:49:59" />
    <file relUrl="Scripts/jquery.quicksearch.js" publishTime="01/10/2012 15:50:00" />
    <file relUrl="Images/gallery/thumb/saibaba3.jpg" publishTime="01/10/2012 15:50:00" />
    <file relUrl="Images/nav_ryt_img_bg.jpg" publishTime="01/10/2012 15:50:00" />
    <file relUrl="Images/gallery/thumb/img4.jpg" publishTime="01/10/2012 15:50:00" />
    <file relUrl="Scripts/jquery.validate.min.js" publishTime="01/10/2012 15:50:00" />
    <file relUrl="Images/navBar1.jpg" publishTime="01/10/2012 15:50:00" />
    <file relUrl="Scripts/MicrosoftMvcAjax.debug.js" publishTime="01/10/2012 15:50:00" />
    <file relUrl="newsletter.html" publishTime="01/10/2012 15:50:00" />
    <file relUrl="Images/inu.gif" publishTime="01/10/2012 15:50:00" />
    <file relUrl="Images/clear.gif" publishTime="01/10/2012 15:49:59" />
    <file relUrl="Content/themes/base/jquery.ui.accordion.css" publishTime="01/10/2012 15:49:59" />
    <file relUrl="Images/gallery/saibaba96.JPG" publishTime="01/10/2012 15:50:00" />
    <file relUrl="Images/gallery/saibaba78.JPG" publishTime="01/10/2012 15:49:59" />
    <file relUrl="Images/nextPageArrowWhite.gif" publishTime="01/10/2012 15:50:00" />
    <file relUrl="Images/donate.jpg" publishTime="01/10/2012 15:49:59" />
    <file relUrl="Images/gallery/thumb/saibaba7.jpg" publishTime="01/10/2012 15:50:00" />
    <file relUrl="bin/EntityFramework.dll" publishTime="01/10/2012 15:49:59" />
    <file relUrl="Images/gallery/saibaba74.JPG" publishTime="01/10/2012 15:49:59" />
    <file relUrl="Scripts/Search.js" publishTime="01/29/2012 13:25:22" />
    <file relUrl="Images/nav_ryt_btm_img_bg.jpg" publishTime="01/10/2012 15:50:00" />
    <file relUrl="Views/Shared/EditUser_control.ascx" publishTime="01/11/2012 16:46:23" />
    <file relUrl="Views/Home/ServicesReceipt.aspx" publishTime="01/26/2012 16:25:28" />
    <file relUrl="Images/welcome.jpg" publishTime="01/10/2012 15:50:00" />
    <file relUrl="Images/gallery/thumb/saibaba9.jpg" publishTime="01/10/2012 15:50:00" />
    <file relUrl="Images/gallery/saibaba48.JPG" publishTime="01/10/2012 15:49:59" />
    <file relUrl="Default.aspx" publishTime="01/10/2012 15:49:59" />
    <file relUrl="Images/gallery/saibaba94.JPG" publishTime="01/10/2012 15:50:00" />
    <file relUrl="Images/arrow.gif" publishTime="01/10/2012 15:49:59" />
    <file relUrl="Scripts/jquery.unobtrusive-ajax.min.js" publishTime="01/10/2012 15:50:00" />
    <file relUrl="Images/gallery/saibaba1.JPG" publishTime="01/10/2012 15:49:59" />
    <file relUrl="Views/Home/PrintReceipt.aspx" publishTime="01/29/2012 11:43:20" />
    <file relUrl="Images/gallery/thumb/saibaba4.jpg" publishTime="01/10/2012 15:50:00" />
    <file relUrl="Views/Reports/ExporttoExcel.aspx" publishTime="01/29/2012 17:01:13" />
    <file relUrl="Images/bg_footer.gif" publishTime="01/10/2012 15:49:59" />
    <file relUrl="Content/style.css" publishTime="01/29/2012 13:52:22" />
    <file relUrl="Scripts/jquery.validate.js" publishTime="01/10/2012 15:50:00" />
    <file relUrl="Views/Shared/Printoptions.aspx" publishTime="01/11/2012 16:32:00" />
    <file relUrl="Images/bg3.gif" publishTime="01/10/2012 15:49:59" />
    <file relUrl="Images/gallery/saibaba72.JPG" publishTime="01/10/2012 15:49:59" />
    <file relUrl="Images/gallery/saibaba36.JPG" publishTime="01/10/2012 15:49:59" />
    <file relUrl="Images/gallery/saibaba76.JPG" publishTime="01/10/2012 15:49:59" />
    <file relUrl="Images/gallery/saibaba24.JPG" publishTime="01/10/2012 15:49:59" />
    <file relUrl="Images/gallery/saibaba.JPG" publishTime="01/10/2012 15:49:59" />
    <file relUrl="donations.html" publishTime="01/10/2012 15:50:00" />
    <file relUrl="Images/gallery/saibaba100.JPG" publishTime="01/10/2012 15:49:59" />
    <file relUrl="Images/gallery/saibaba56.JPG" publishTime="01/10/2012 15:49:59" />
    <file relUrl="Images/gallery/saibaba5.JPG" publishTime="01/10/2012 15:49:59" />
    <file relUrl="Images/gallery/saibaba30.JPG" publishTime="01/10/2012 15:49:59" />
    <file relUrl="Images/gallery/thumb/img3.jpg" publishTime="01/10/2012 15:50:00" />
    <file relUrl="Scripts/common.js" publishTime="01/10/2012 15:50:00" />
    <file relUrl="saibaba.png" publishTime="01/10/2012 15:50:00" />
    <file relUrl="Content/status.css" publishTime="01/29/2012 14:14:26" />
    <file relUrl="bin/saibabacharityreceiptorDL.pdb" publishTime="01/30/2012 17:47:21" />
    <file relUrl="Images/nav_lft_btm_img_bg.jpg" publishTime="01/10/2012 15:50:00" />
    <file relUrl="Views/Controlpanel/ImportfromExcel.aspx" publishTime="01/29/2012 11:43:20" />
    <file relUrl="Images/face.gif" publishTime="01/10/2012 15:49:59" />
    <file relUrl="Images/gallery/thumb/saibaba99.jpg" publishTime="01/10/2012 15:50:00" />
    <file relUrl="Images/rt-pan-top.gif" publishTime="01/10/2012 15:50:00" />
    <file relUrl="Views/Account/ChangePassword.aspx" publishTime="01/10/2012 15:50:00" />
    <file relUrl="Images/gallery/saibaba104.JPG" publishTime="01/10/2012 15:49:59" />
    <file relUrl="Images/gallery/saibaba52.JPG" publishTime="01/10/2012 15:49:59" />
    <file relUrl="Images/gallery/saibaba34.JPG" publishTime="01/10/2012 15:49:59" />
    <file relUrl="Images/fancybox/fancy_shadow_nw.png" publishTime="01/10/2012 15:49:59" />
    <file relUrl="Views/Home/EditMerchandiseReceipt.aspx" publishTime="01/26/2012 16:12:17" />
    <file relUrl="Scripts/Reports.js" publishTime="01/26/2012 15:24:11" />
    <file relUrl="Views/Account/LogOnPage.aspx" publishTime="01/26/2012 13:04:04" />
    <file relUrl="Images/gallery/saibaba75.JPG" publishTime="01/10/2012 15:49:59" />
    <file relUrl="Views/Home/MerchandiseReceipt.aspx" publishTime="01/26/2012 16:11:09" />
    <file relUrl="Images/nav_left_img_bg.jpg" publishTime="01/10/2012 15:50:00" />
    <file relUrl="Images/QR.jpg" publishTime="01/10/2012 15:49:59" />
    <file relUrl="Views/Account/Logon_Ctrl.ascx" publishTime="01/26/2012 13:05:39" />
    <file relUrl="Images/gallery/saibaba2.JPG" publishTime="01/10/2012 15:49:59" />
    <file relUrl="Images/ui-bg_diagonals-thick_18_b81900_40x40.png" publishTime="01/10/2012 15:50:00" />
    <file relUrl="Content/themes/base/jquery.ui.autocomplete.css" publishTime="01/10/2012 15:49:59" />
    <file relUrl="Views/Shared/Site.Master" publishTime="01/10/2012 15:50:00" />
    <file relUrl="Images/ui-bg_highlight-soft_75_ffe45c_1x100.png" publishTime="01/10/2012 15:50:00" />
    <file relUrl="Images/secure90x72.gif" publishTime="01/10/2012 15:50:00" />
    <file relUrl="packages.config" publishTime="01/10/2012 15:50:00" />
    <file relUrl="Images/fancybox/fancy_shadow_ne.png" publishTime="01/10/2012 15:49:59" />
    <file relUrl="Images/gallery/thumb/saibaba112.jpg" publishTime="01/10/2012 15:50:00" />
    <file relUrl="Images/gallery/thumb/saibaba2.jpg" publishTime="01/10/2012 15:50:00" />
    <file relUrl="Images/fancybox/fancy_nav_left.png" publishTime="01/10/2012 15:49:59" />
    <file relUrl="Images/page_cont_lft_img_bg.jpg" publishTime="01/10/2012 15:50:00" />
    <file relUrl="Images/gallery/saibaba9.JPG" publishTime="01/10/2012 15:50:00" />
    <file relUrl="Images/gallery/saibaba71.JPG" publishTime="01/10/2012 15:49:59" />
    <file relUrl="Images/gallery/saibaba26.JPG" publishTime="01/10/2012 15:49:59" />
    <file relUrl="Scripts/MicrosoftMvcValidation.js" publishTime="01/10/2012 15:50:00" />
    <file relUrl="Images/gallery/thumb/saibaba106.jpg" publishTime="01/10/2012 15:50:00" />
    <file relUrl="Content/Site.css" publishTime="01/10/2012 15:49:59" />
    <file relUrl="Images/gallery/saibaba6.JPG" publishTime="01/10/2012 15:49:59" />
    <file relUrl="Images/janmashtami2011.jpg" publishTime="01/10/2012 15:50:00" />
    <file relUrl="Content/themes/base/images/ui-bg_highlight-soft_75_cccccc_1x100.png" publishTime="01/10/2012 15:49:59" />
    <file relUrl="Content/themes/base/jquery.ui.selectable.css" publishTime="01/10/2012 15:49:59" />
    <file relUrl="Images/gallery/thumb/saibaba5.jpg" publishTime="01/10/2012 15:50:00" />
    <file relUrl="Views/Home/PrintServicesReceipt.aspx" publishTime="01/29/2012 11:43:20" />
    <file relUrl="Images/gallery/saibaba108.JPG" publishTime="01/10/2012 15:49:59" />
    <file relUrl="Views/Web.config" publishTime="01/10/2012 15:50:00" />
    <file relUrl="Images/gallery/saibaba38.JPG" publishTime="01/10/2012 15:49:59" />
    <file relUrl="Content/themes/base/jquery.ui.core.css" publishTime="01/10/2012 15:49:59" />
    <file relUrl="Content/themes/base/jquery.ui.progressbar.css" publishTime="01/10/2012 15:49:59" />
    <file relUrl="Scripts/jquery-1.3.2.js" publishTime="01/10/2012 15:50:00" />
    <file relUrl="Views/Controlpanel/AddUser.aspx" publishTime="01/10/2012 15:50:00" />
    <file relUrl="bin/saibabacharityreceiptor.pdb" publishTime="01/30/2012 18:09:03" />
    <file relUrl="Images/gallery/saibaba107.JPG" publishTime="01/10/2012 15:49:59" />
    <file relUrl="Views/Shared/Error.aspx" publishTime="01/10/2012 15:50:00" />
    <file relUrl="Views/Reports/ServicesReceipts.aspx" publishTime="01/26/2012 16:08:13" />
    <file relUrl="Images/bg_rtContent.gif" publishTime="01/10/2012 15:49:59" />
    <file relUrl="Scripts/jquery.validate.unobtrusive.js" publishTime="01/10/2012 15:50:00" />
    <file relUrl="Views/Controlpanel/EditUser.aspx" publishTime="01/26/2012 12:20:39" />
    <file relUrl="Images/gallery/saibaba99.JPG" publishTime="01/10/2012 15:50:00" />
    <file relUrl="Images/gallery/saibaba65.JPG" publishTime="01/10/2012 15:49:59" />
    <file relUrl="Images/saibaba.png" publishTime="01/10/2012 15:50:00" />
    <file relUrl="Content/themes/base/images/ui-icons_888888_256x240.png" publishTime="01/10/2012 15:49:59" />
    <file relUrl="Scripts/jquery-ui-1.8.11.js" publishTime="01/10/2012 15:50:00" />
    <file relUrl="Images/gallery/saibaba35.JPG" publishTime="01/10/2012 15:49:59" />
    <file relUrl="Images/fancybox/fancy_shadow_w.png" publishTime="01/10/2012 15:49:59" />
    <file relUrl="Images/gallery/saibaba42.JPG" publishTime="01/10/2012 15:49:59" />
    <file relUrl="Images/gallery/saibaba22.JPG" publishTime="01/10/2012 15:49:59" />
    <file relUrl="Images/gallery/saibaba3.JPG" publishTime="01/10/2012 15:49:59" />
    <file relUrl="Content/themes/base/images/ui-bg_glass_95_fef1ec_1x400.png" publishTime="01/10/2012 15:49:59" />
    <file relUrl="Images/ico-delete.gif" publishTime="01/10/2012 15:50:00" />
    <file relUrl="Images/gallery/saibaba32.JPG" publishTime="01/10/2012 15:49:59" />
    <file relUrl="Images/gallery/saibaba61.JPG" publishTime="01/10/2012 15:49:59" />
    <file relUrl="Images/specialbg.jpg" publishTime="01/10/2012 15:50:00" />
    <file relUrl="Images/fancybox/fancy_shadow_n.png" publishTime="01/10/2012 15:49:59" />
    <file relUrl="Views/Home/RecurringReceipt_Ctrl.ascx" publishTime="01/26/2012 15:23:28" />
    <file relUrl="Images/gallery/saibaba113.JPG" publishTime="01/10/2012 15:49:59" />
    <file relUrl="Images/gallery/saibaba57.JPG" publishTime="01/10/2012 15:49:59" />
    <file relUrl="Scripts/jquery-ui-1.8.16.custom.min.js" publishTime="01/10/2012 15:50:00" />
    <file relUrl="Content/controlpanel.css" publishTime="01/10/2012 15:49:59" />
    <file relUrl="Images/header_top_img_bg.jpg" publishTime="01/10/2012 15:50:00" />
    <file relUrl="Content/themes/base/jquery.ui.button.css" publishTime="01/10/2012 15:49:59" />
    <file relUrl="abouttemple.html" publishTime="01/10/2012 15:50:00" />
    <file relUrl="Images/gallery/saibaba103.JPG" publishTime="01/10/2012 15:49:59" />
    <file relUrl="Content/themes/base/images/ui-bg_glass_75_e6e6e6_1x400.png" publishTime="01/10/2012 15:49:59" />
    <file relUrl="Images/gallery/saibaba79.JPG" publishTime="01/10/2012 15:49:59" />
    <file relUrl="Content/themes/base/jquery.ui.slider.css" publishTime="01/10/2012 15:49:59" />
    <file relUrl="Images/under.jpg" publishTime="01/10/2012 15:50:00" />
    <file relUrl="Images/bg_mainCont.gif" publishTime="01/10/2012 15:49:59" />
    <file relUrl="Scripts/jquery-1.5.1.js" publishTime="01/10/2012 15:50:00" />
    <file relUrl="Content/themes/base/jquery.ui.theme.css" publishTime="01/10/2012 15:49:59" />
    <file relUrl="Images/gallery/saibaba12.JPG" publishTime="01/10/2012 15:49:59" />
    <file relUrl="Images/gallery/saibaba117.JPG" publishTime="01/10/2012 15:49:59" />
    <file relUrl="Images/gallery/saibaba53.JPG" publishTime="01/10/2012 15:49:59" />
    <file relUrl="Scripts/jquery.history.js" publishTime="01/10/2012 15:50:00" />
    <file relUrl="bin/Telerik.OpenAccess.Query.xml" publishTime="04/05/2009 22:39:40" />
    <file relUrl="Images/rt-pan-bot.gif" publishTime="01/10/2012 15:50:00" />
    <file relUrl="Content/themes/base/jquery.ui.base.css" publishTime="01/10/2012 15:49:59" />
    <file relUrl="bin/BarcodeGenerator.Common.dll" publishTime="05/03/2009 14:09:18" />
    <file relUrl="index.html" publishTime="01/10/2012 15:50:00" />
    <file relUrl="Content/themes/base/images/ui-bg_glass_55_fbf9ee_1x400.png" publishTime="01/10/2012 15:49:59" />
    <file relUrl="Images/gallery/saibaba90.JPG" publishTime="01/10/2012 15:50:00" />
    <file relUrl="Scripts/jquery.opacityrollover.js" publishTime="01/10/2012 15:50:00" />
    <file relUrl="Images/ui-bg_glass_65_ffffff_1x400.png" publishTime="01/10/2012 15:50:00" />
    <file relUrl="Images/gallery/saibaba16.JPG" publishTime="01/10/2012 15:49:59" />
    <file relUrl="Content/themes/base/images/ui-icons_2e83ff_256x240.png" publishTime="01/10/2012 15:49:59" />
    <file relUrl="Images/rt-pan-botlet.gif" publishTime="01/10/2012 15:50:00" />
    <file relUrl="Images/gallery/saibaba120.jpg" publishTime="01/10/2012 15:49:59" />
    <file relUrl="Views/Reports/RegularReceipts.aspx" publishTime="01/26/2012 12:16:01" />
    <file relUrl="Images/gallery/saibaba91.JPG" publishTime="01/10/2012 15:50:00" />
    <file relUrl="Images/gallery/thumb/saibaba107.jpg" publishTime="01/10/2012 15:50:00" />
    <file relUrl="Images/gallery/saibaba31.JPG" publishTime="01/10/2012 15:49:59" />
    <file relUrl="Views/Controlpanel/Reports.aspx" publishTime="01/11/2012 19:16:34" />
    <file relUrl="Views/Shared/Status.aspx" publishTime="01/29/2012 14:06:19" />
    <file relUrl="Images/fancybox/fancy_loading.png" publishTime="01/10/2012 15:49:59" />
    <file relUrl="Scripts/excelImport.js" publishTime="01/10/2012 17:50:29" />
    <file relUrl="Images/gallery/img3.jpg" publishTime="01/10/2012 15:49:59" />
    <file relUrl="Scripts/MicrosoftAjax.js" publishTime="01/10/2012 15:50:00" />
    <file relUrl="Views/Home/RegularReceipt_Ctrl.ascx" publishTime="01/26/2012 15:23:33" />
    <file relUrl="Content/themes/base/jquery.ui.resizable.css" publishTime="01/10/2012 15:49:59" />
    <file relUrl="Views/Home/ServicesReceipt_Ctrl.ascx" publishTime="01/26/2012 16:24:32" />
    <file relUrl="Content/themes/base/images/ui-icons_222222_256x240.png" publishTime="01/10/2012 15:49:59" />
    <file relUrl="bin/saibabacharityreceiptor.dll" publishTime="01/30/2012 18:09:04" />
    <file relUrl="signup.html" publishTime="01/10/2012 15:50:00" />
    <file relUrl="Images/header_btm_bg_img.jpg" publishTime="01/10/2012 15:50:00" />
    <file relUrl="Images/bg2.gif" publishTime="01/10/2012 15:49:59" />
    <file relUrl="Images/gallery/saibaba124.jpg" publishTime="01/10/2012 15:49:59" />
    <file relUrl="Images/gallery/saibaba95.JPG" publishTime="01/10/2012 15:50:00" />
    <file relUrl="Images/gallery/saibaba69.JPG" publishTime="01/10/2012 15:49:59" />
    <file relUrl="Images/gallery/saibab127.jpg" publishTime="01/10/2012 15:49:59" />
    <file relUrl="Images/fancybox/blank.gif" publishTime="01/10/2012 15:49:59" />
    <file relUrl="Scripts/Users.js" publishTime="01/11/2012 17:37:19" />
    <file relUrl="Web.config" publishTime="01/30/2012 18:10:00" />
    <file relUrl="Scripts/MicrosoftMvcValidation.debug.js" publishTime="01/10/2012 15:50:00" />
    <file relUrl="Images/navBar.jpg" publishTime="01/10/2012 15:50:00" />
    <file relUrl="Images/add.jpg" publishTime="01/26/2012 11:11:07" />
    <file relUrl="Images/bg1.gif" publishTime="01/10/2012 15:49:59" />
    <file relUrl="Content/themes/base/jquery.ui.all.css" publishTime="01/10/2012 15:49:59" />
    <file relUrl="Images/gallery/saibab126.jpg" publishTime="01/10/2012 15:49:59" />
    <file relUrl="Content/themes/base/images/ui-bg_glass_65_ffffff_1x400.png" publishTime="01/10/2012 15:49:59" />
    <file relUrl="Views/Home/EditServicesReceipt.aspx" publishTime="01/26/2012 16:30:17" />
    <file relUrl="Views/Home/MerchandiseReceipt_Ctrl.ascx" publishTime="01/26/2012 16:19:21" />
    <file relUrl="Content/FormLayout.css" publishTime="01/29/2012 14:04:05" />
    <file relUrl="Views/Reports/MerchandiseReceipts.aspx" publishTime="01/26/2012 16:07:18" />
    <file relUrl="Images/gallery/saibaba54.JPG" publishTime="01/10/2012 15:49:59" />
    <file relUrl="Views/Account/ChangePasswordSuccess.aspx" publishTime="01/10/2012 15:50:00" />
    <file relUrl="Views/Home/RecurringReceipt.aspx" publishTime="01/26/2012 14:11:15" />
    <file relUrl="Images/gallery/thumb/img1.jpg" publishTime="01/10/2012 15:50:00" />
    <file relUrl="Images/fancybox/fancy_shadow_e.png" publishTime="01/10/2012 15:49:59" />
    <file relUrl="Scripts/JQValidation.js" publishTime="01/10/2012 15:50:00" />
    <file relUrl="Scripts/MicrosoftMvcAjax.js" publishTime="01/10/2012 15:50:00" />
    <file relUrl="Content/jquery-ui-1.8.16.custom.css" publishTime="01/10/2012 15:49:59" />
    <file relUrl="Images/gallery/saibaba55.JPG" publishTime="01/10/2012 15:49:59" />
    <file relUrl="Images/gallery/saibaba21.JPG" publishTime="01/10/2012 15:49:59" />
    <file relUrl="Images/fancybox/fancybox-y.png" publishTime="01/10/2012 15:49:59" />
    <file relUrl="Images/fancybox/fancy_shadow_s.png" publishTime="01/10/2012 15:49:59" />
    <file relUrl="Images/fancybox/fancy_title_left.png" publishTime="01/10/2012 15:49:59" />
    <file relUrl="bin/EntityFramework.xml" publishTime="01/10/2012 15:49:59" />
    <file relUrl="Images/donate-inn.gif" publishTime="01/10/2012 15:49:59" />
    <file relUrl="Content/themes/base/jquery.ui.datepicker.css" publishTime="01/10/2012 15:49:59" />
    <file relUrl="Images/gallery/saibaba50.JPG" publishTime="01/10/2012 15:49:59" />
  </publishProfile>
</publishData>